LICENSE
pytime_converter/__init__.py
pytime_converter/helper/__init__.py
pytime_converter/helper/input_regex_parser.py
pytime_converter/helper/recognized_unit_measure.py
pytime_converter/service/convert_service.py
pytime_converter-0.1.8.dist-info/LICENSE
pytime_converter-0.1.8.dist-info/WHEEL
pytime_converter-0.1.8.dist-info/METADATA
pytime_converter-0.1.8.dist-info/RECORD
