Metadata-Version: 2.1
Name: pytime-converter
Version: 0.1.8
Summary: Easily convert differt time-range format to standard ones
Home-page: https://github.com/massicer/PyTime-Converter
License: GPL-3.0-only
Keywords: env,converter,time-range,time,python
Author: Massimiliano Ceriani
Author-email: massimiliano.ceriani08@gmail.com
Requires-Python: >=3.7,<4.0
Classifier: Environment :: Plugins
Classifier: License :: OSI Approved :: GNU General Public License v3 (GPLv3)
Classifier: Operating System :: OS Independent
Classifier: Programming Language :: Python :: 3
Classifier: Programming Language :: Python :: 3.7
Project-URL: Repository, https://github.com/massicer/PyTime-Converter
